bfqcircuits/__init__.py
bfqcircuits/core/__init__.py
bfqcircuits/core/fit_fluxonium.py
bfqcircuits/core/fluxonium.py
bfqcircuits/core/fluxonium_LCAO.py
bfqcircuits/core/resonator_TLS.py
bfqcircuits/core/resonator_fluxonium.py
bfqcircuits/core/resonator_transmon.py
bfqcircuits/core/transmon.py
bfqcircuits/utils/__init__.py
bfqcircuits/utils/resonator_atom.py
bfqcircuits/utils/special.py
bfqcircuits-0.2.1.dist-info/LICENSE.md
bfqcircuits-0.2.1.dist-info/METADATA
bfqcircuits-0.2.1.dist-info/WHEEL
bfqcircuits-0.2.1.dist-info/top_level.txt
bfqcircuits-0.2.1.dist-info/zip-safe
bfqcircuits-0.2.1.dist-info/RECORD
