Metadata-Version: 2.1
Name: bfqcircuits
Version: 0.2.1
Summary: Superconducting circuit quantization
Author-email: Martin Spiecker <47812395+MartinSpiecker@users.noreply.github.com>
Maintainer-email: Martin Spiecker <47812395+MartinSpiecker@users.noreply.github.com>
License: Copyright (c) 2024. Martin Spiecker. All rights reserved.
Project-URL: Homepage, https://github.com/MartinSpiecker/bfqcircuits
Project-URL: Bug Reports, https://github.com/MartinSpiecker/bfqcircuits/issues
Project-URL: Source Code, https://github.com/MartinSpiecker/bfqcircuits
Project-URL: Documentation, https://black-forest-quantum-circuits.readthedocs.io/en/latest/index.html
Keywords: bfqcircuits
Classifier: Development Status :: 4 - Beta
Classifier: Topic :: Software Development :: Libraries :: Python Modules
Classifier: License :: OSI Approved :: BSD License
Classifier: Programming Language :: Python :: 3 :: Only
Classifier: Programming Language :: Python :: 3.10
Classifier: Programming Language :: Python :: 3.11
Classifier: Programming Language :: Python :: 3.12
Requires-Python: >=3.10
License-File: LICENSE.md
Requires-Dist: numpy
Requires-Dist: scipy
Requires-Dist: matplotlib
Requires-Dist: schemdraw
Provides-Extra: develop
Requires-Dist: ruff ; extra == 'develop'
Provides-Extra: docs
Requires-Dist: sphinx ; extra == 'docs'
Requires-Dist: nbsphinx ; extra == 'docs'
Requires-Dist: sphinx-rtd-theme ; extra == 'docs'
Provides-Extra: tests
Requires-Dist: coverage[toml] ; extra == 'tests'
Requires-Dist: pytest ; extra == 'tests'
